ZhuanWeiChengxuyuanBianxieDeYingyuXuexizhinan/README.md
ZhuanWeiChengxuyuanBianxieDeYingyuXuexizhinan/__init__.py
ZhuanWeiChengxuyuanBianxieDeYingyuXuexizhinan/__main__.py
ZhuanWeiChengxuyuanBianxieDeYingyuXuexizhinan/file.epub
ZhuanWeiChengxuyuanBianxieDeYingyuXuexizhinan/index.html
ZhuanWeiChengxuyuanBianxieDeYingyuXuexizhinan/css/__init__.py
ZhuanWeiChengxuyuanBianxieDeYingyuXuexizhinan/css/annotations.css
ZhuanWeiChengxuyuanBianxieDeYingyuXuexizhinan/css/main.css
ZhuanWeiChengxuyuanBianxieDeYingyuXuexizhinan/css/normalize.css
ZhuanWeiChengxuyuanBianxieDeYingyuXuexizhinan/css/popup.css
ZhuanWeiChengxuyuanBianxieDeYingyuXuexizhinan/font/__init__.py
ZhuanWeiChengxuyuanBianxieDeYingyuXuexizhinan/font/fontello.eot
ZhuanWeiChengxuyuanBianxieDeYingyuXuexizhinan/font/fontello.svg
ZhuanWeiChengxuyuanBianxieDeYingyuXuexizhinan/font/fontello.ttf
ZhuanWeiChengxuyuanBianxieDeYingyuXuexizhinan/font/fontello.woff
ZhuanWeiChengxuyuanBianxieDeYingyuXuexizhinan/img/__init__.py
ZhuanWeiChengxuyuanBianxieDeYingyuXuexizhinan/img/annotator-glyph-sprite.png
ZhuanWeiChengxuyuanBianxieDeYingyuXuexizhinan/img/annotator-icon-sprite.png
ZhuanWeiChengxuyuanBianxieDeYingyuXuexizhinan/img/apple-touch-icon.png
ZhuanWeiChengxuyuanBianxieDeYingyuXuexizhinan/img/cancelfullscreen.png
ZhuanWeiChengxuyuanBianxieDeYingyuXuexizhinan/img/close.png
ZhuanWeiChengxuyuanBianxieDeYingyuXuexizhinan/img/fullscreen.png
ZhuanWeiChengxuyuanBianxieDeYingyuXuexizhinan/img/loader.gif
ZhuanWeiChengxuyuanBianxieDeYingyuXuexizhinan/img/menu-icon.png
ZhuanWeiChengxuyuanBianxieDeYingyuXuexizhinan/img/save.png
ZhuanWeiChengxuyuanBianxieDeYingyuXuexizhinan/img/saved.png
ZhuanWeiChengxuyuanBianxieDeYingyuXuexizhinan/img/settings-s.png
ZhuanWeiChengxuyuanBianxieDeYingyuXuexizhinan/img/settings.png
ZhuanWeiChengxuyuanBianxieDeYingyuXuexizhinan/img/star.png
ZhuanWeiChengxuyuanBianxieDeYingyuXuexizhinan/js/__init__.py
ZhuanWeiChengxuyuanBianxieDeYingyuXuexizhinan/js/epub.js
zhuan_wei_chengxuyuan_bianxie_de_yingyu_xuexizhinan-2024.3.5.0.dist-info/METADATA
zhuan_wei_chengxuyuan_bianxie_de_yingyu_xuexizhinan-2024.3.5.0.dist-info/WHEEL
zhuan_wei_chengxuyuan_bianxie_de_yingyu_xuexizhinan-2024.3.5.0.dist-info/entry_points.txt
zhuan_wei_chengxuyuan_bianxie_de_yingyu_xuexizhinan-2024.3.5.0.dist-info/top_level.txt
zhuan_wei_chengxuyuan_bianxie_de_yingyu_xuexizhinan-2024.3.5.0.dist-info/RECORD
